[
    {
        "ProductID": 184145401,
        "ProductName": "OTJCwRdIKAVuGEWQaxdxInokdseBYXhA",
        "SupplierID": 1692177052,
        "CategoryID": 207900661,
        "QuantityPerUnit": "QuantityPerUnit1",
        "UnitPrice": 6328878947.5336,
        "UnitsInStock": 22405,
        "UnitsOnOrder": 31927,
        "ReorderLevel": 14424,
        "Discontinued": false,
        "CategoryName": "FDprQJqSysEJXKF"
    },
    {
        "ProductID": 561198967,
        "ProductName": "uHiUmUgIvfqrCMumMmhLPGipXGKBShFC",
        "SupplierID": 151288563,
        "CategoryID": 950948458,
        "QuantityPerUnit": "QuantityPerUnit2",
        "UnitPrice": 70158927980.8104,
        "UnitsInStock": 5031,
        "UnitsOnOrder": 20239,
        "ReorderLevel": 21529,
        "Discontinued": true,
        "CategoryName": "BBTqhpKZkPrtjNH"
    },
    {
        "ProductID": 201273162,
        "ProductName": "fBvLEByQQgZLUcYfjaYiyGzkqrGVlhAA",
        "SupplierID": 1223796907,
        "CategoryID": 1545048574,
        "QuantityPerUnit": "QuantityPerUnit3",
        "UnitPrice": 8408578322.269,
        "UnitsInStock": 17460,
        "UnitsOnOrder": 17266,
        "ReorderLevel": 29501,
        "Discontinued": false,
        "CategoryName": "hlUhJrULvtDlTMB"
    },
    {
        "ProductID": 246750423,
        "ProductName": "jaZTEZvfjUraLkxwrbHoQfNUTvaqLcNa",
        "SupplierID": 786049561,
        "CategoryID": 115827557,
        "QuantityPerUnit": "QuantityPerUnit4",
        "UnitPrice": 29603930539.4515,
        "UnitsInStock": 2132,
        "UnitsOnOrder": 26983,
        "ReorderLevel": 2855,
        "Discontinued": false,
        "CategoryName": "DmRfnptgryzYCTA"
    },
    {
        "ProductID": 1350334669,
        "ProductName": "jehsGQyeCiRBUfxuiidCsNbYgmpeFLRc",
        "SupplierID": 534495685,
        "CategoryID": 855581698,
        "QuantityPerUnit": "QuantityPerUnit5",
        "UnitPrice": 69462853274.3081,
        "UnitsInStock": 23343,
        "UnitsOnOrder": 15795,
        "ReorderLevel": 5807,
        "Discontinued": true,
        "CategoryName": "XXhWUKMImNIMlIx"
    },
    {
        "ProductID": 1929968756,
        "ProductName": "sLpdsNeyvoXKNThpTwrcjLrBKtqPCUid",
        "SupplierID": 893358554,
        "CategoryID": 1722316290,
        "QuantityPerUnit": "QuantityPerUnit6",
        "UnitPrice": 93131633009.7615,
        "UnitsInStock": 4621,
        "UnitsOnOrder": 4629,
        "ReorderLevel": 31615,
        "Discontinued": false,
        "CategoryName": "gHnNPyIvJGuKVes"
    },
    {
        "ProductID": 465410114,
        "ProductName": "YxJyDAWiAMbJvtNvCqSUvVJqjNaBPWJD",
        "SupplierID": 1003787531,
        "CategoryID": 38163872,
        "QuantityPerUnit": "QuantityPerUnit7",
        "UnitPrice": 55093557410.8734,
        "UnitsInStock": 2962,
        "UnitsOnOrder": 16358,
        "ReorderLevel": 30894,
        "Discontinued": true,
        "CategoryName": "xwrDQJTUTluCUug"
    },
    {
        "ProductID": 892833429,
        "ProductName": "UYuYzsnYOkMriNuqlsFbdDwcEUXxGCOK",
        "SupplierID": 1527729915,
        "CategoryID": 1542455159,
        "QuantityPerUnit": "QuantityPerUnit8",
        "UnitPrice": 17778028501.1976,
        "UnitsInStock": 8840,
        "UnitsOnOrder": 26723,
        "ReorderLevel": 22806,
        "Discontinued": true,
        "CategoryName": "cnXIgjAZrpKCEyr"
    },
    {
        "ProductID": 112147484,
        "ProductName": "qZaMqsfdagQaympTjyzvmwVALfDxcypK",
        "SupplierID": 526654930,
        "CategoryID": 485260651,
        "QuantityPerUnit": "QuantityPerUnit9",
        "UnitPrice": 38156469538.8078,
        "UnitsInStock": 21158,
        "UnitsOnOrder": 22797,
        "ReorderLevel": 31551,
        "Discontinued": false,
        "CategoryName": "gxKPLoSLOkWcstW"
    },
    {
        "ProductID": 1105087751,
        "ProductName": "CCHjbHdhAOlPyUxLmkJlafYUpkwqhAtG",
        "SupplierID": 1534652984,
        "CategoryID": 2111237061,
        "QuantityPerUnit": "QuantityPerUnit10",
        "UnitPrice": 7738480810.0759,
        "UnitsInStock": 21158,
        "UnitsOnOrder": 24375,
        "ReorderLevel": 21643,
        "Discontinued": true,
        "CategoryName": "nUPwvttHhmbgXbB"
    },
    {
        "ProductID": 837391611,
        "ProductName": "dQQivTUlGgSJOtSMxyFXLameLbyCHARa",
        "SupplierID": 430813457,
        "CategoryID": 1754214593,
        "QuantityPerUnit": "QuantityPerUnit11",
        "UnitPrice": 99217167752.7949,
        "UnitsInStock": 13390,
        "UnitsOnOrder": 24649,
        "ReorderLevel": 27583,
        "Discontinued": true,
        "CategoryName": "EbAKavykmjmhbOj"
    },
    {
        "ProductID": 517443774,
        "ProductName": "hdArKUrCiQrWcXTAmEKnlDtxbjFJArna",
        "SupplierID": 556617134,
        "CategoryID": 779691698,
        "QuantityPerUnit": "QuantityPerUnit12",
        "UnitPrice": 55033346335.4036,
        "UnitsInStock": 26826,
        "UnitsOnOrder": 12869,
        "ReorderLevel": 13634,
        "Discontinued": true,
        "CategoryName": "ZuIzJpseCOwnRmv"
    },
    {
        "ProductID": 171972009,
        "ProductName": "CuoYWvmsTwMHrYGQecnhwQlIdQPubmkp",
        "SupplierID": 1676358672,
        "CategoryID": 553880847,
        "QuantityPerUnit": "QuantityPerUnit13",
        "UnitPrice": 11086719948.7984,
        "UnitsInStock": 30376,
        "UnitsOnOrder": 8636,
        "ReorderLevel": 24734,
        "Discontinued": true,
        "CategoryName": "rwtqomchlOLyQWP"
    },
    {
        "ProductID": 1937067588,
        "ProductName": "uvekEkuZtgnnguTJJWSSPjmGcxdGGbfm",
        "SupplierID": 1007892644,
        "CategoryID": 2103140074,
        "QuantityPerUnit": "QuantityPerUnit14",
        "UnitPrice": 47485921299.085,
        "UnitsInStock": 11874,
        "UnitsOnOrder": 8049,
        "ReorderLevel": 4531,
        "Discontinued": false,
        "CategoryName": "nVIQzLzWVzIzjaH"
    },
    {
        "ProductID": 468399700,
        "ProductName": "wsXMPbdDxtEydhFmffrupvuDkcXrItob",
        "SupplierID": 1647483619,
        "CategoryID": 489979668,
        "QuantityPerUnit": "QuantityPerUnit15",
        "UnitPrice": 63636758062.0571,
        "UnitsInStock": 7397,
        "UnitsOnOrder": 3608,
        "ReorderLevel": 13096,
        "Discontinued": true,
        "CategoryName": "DowxgGQmQlyGUvy"
    },
    {
        "ProductID": 1522810812,
        "ProductName": "FumkvZsFmvBudINQOGEchnIvGVdFMhhP",
        "SupplierID": 122954064,
        "CategoryID": 41827209,
        "QuantityPerUnit": "QuantityPerUnit16",
        "UnitPrice": 24757118197.1579,
        "UnitsInStock": 12265,
        "UnitsOnOrder": 26127,
        "ReorderLevel": 16072,
        "Discontinued": false,
        "CategoryName": "EqiWNtlOTppRIhn"
    },
    {
        "ProductID": 1122209437,
        "ProductName": "UosYDvdpmKJBjgVtSdSScLdFFVJwBomG",
        "SupplierID": 686202651,
        "CategoryID": 658298069,
        "QuantityPerUnit": "QuantityPerUnit17",
        "UnitPrice": 55076542426.832,
        "UnitsInStock": 18119,
        "UnitsOnOrder": 17532,
        "ReorderLevel": 25111,
        "Discontinued": false,
        "CategoryName": "GjJmODbrbIqmMOX"
    },
    {
        "ProductID": 1992624549,
        "ProductName": "bBfgjAhHJUMvChDLuTKKKMOljsvflfyj",
        "SupplierID": 595062413,
        "CategoryID": 1042789073,
        "QuantityPerUnit": "QuantityPerUnit18",
        "UnitPrice": 21850222256.0346,
        "UnitsInStock": 11309,
        "UnitsOnOrder": 20835,
        "ReorderLevel": 19135,
        "Discontinued": true,
        "CategoryName": "IvgqVfemiPlMrgZ"
    },
    {
        "ProductID": 2001424079,
        "ProductName": "yxsnjxfEgfjRdSjwhLtXnzRDEGZTYPQF",
        "SupplierID": 1472047093,
        "CategoryID": 151950691,
        "QuantityPerUnit": "QuantityPerUnit19",
        "UnitPrice": 29922645399.3469,
        "UnitsInStock": 13834,
        "UnitsOnOrder": 22207,
        "ReorderLevel": 32238,
        "Discontinued": true,
        "CategoryName": "IWGhOWSeifvmsjx"
    },
    {
        "ProductID": 2094248672,
        "ProductName": "LCQbaOibUFJjSaiDPJrkeFpYVoijffVm",
        "SupplierID": 1058984671,
        "CategoryID": 2136668707,
        "QuantityPerUnit": "QuantityPerUnit20",
        "UnitPrice": 1378423580.8998,
        "UnitsInStock": 19081,
        "UnitsOnOrder": 20208,
        "ReorderLevel": 2503,
        "Discontinued": true,
        "CategoryName": "UJQpYCwMdYNlsAA"
    }
]